<?xml version="1.0" encoding="UTF-8"?><record_update table="sys_ux_client_script">
    <sys_ux_client_script action="DELETE">
        <includes/>
        <macroponent display_value="Landing Page">d6177aeb2b132110cc0109b2ef4e3755</macroponent>
        <name>data_row_3_data</name>
        <preset/>
        <required_translations>[ {
  "code" : null,
  "message" : "{0} out of 5",
  "comment" : ""
} ]</required_translations>
        <script><![CDATA[/**
 * @param {params} params
 * @param {api} params.api
 * @param {TransformApiHelpers} params.helpers
 */
function evaluateProperty({
    api,
    helpers
}) {
    const input = api.data.evam_popular_articles.compositeDataViews;
    for (var i = 0; i < input.items.length; i++) {
        var model = input.items[i].propValues;
        if (model.model.rating != "") {
            model.detailValueTwo = helpers.translateSync("{0} out of 5", model.model.rating);
        }
    }
    return input;
}]]></script>
        <script_api_version>2.0.0</script_api_version>
        <sys_class_name>sys_ux_client_script</sys_class_name>
        <sys_created_by>system</sys_created_by>
        <sys_created_on>2023-06-14 11:48:11</sys_created_on>
        <sys_id>16177aebe5132110e72aa2e74adf8449</sys_id>
        <sys_mod_count>0</sys_mod_count>
        <sys_name>data_row_3_data</sys_name>
        <sys_package display_value="Flow Finder" source="x_350851_flow_fi_0">18d672eb97132110974bbf1e6253afc8</sys_package>
        <sys_policy/>
        <sys_scope display_value="Flow Finder">18d672eb97132110974bbf1e6253afc8</sys_scope>
        <sys_update_name>sys_ux_client_script_16177aebe5132110e72aa2e74adf8449</sys_update_name>
        <sys_updated_by>system</sys_updated_by>
        <sys_updated_on>2023-06-14 11:48:11</sys_updated_on>
        <target/>
        <type>transform</type>
    </sys_ux_client_script>
    <sys_update_version action="INSERT_OR_UPDATE">
        <action>DELETE</action>
        <application display_value="Flow Finder">18d672eb97132110974bbf1e6253afc8</application>
        <file_path/>
        <instance_id>1636d6e86f6af900d54da9cc5d3ee472</instance_id>
        <instance_name>dev10498</instance_name>
        <name>sys_ux_client_script_16177aebe5132110e72aa2e74adf8449</name>
        <payload>&lt;?xml version="1.0" encoding="UTF-8"?&gt;&lt;record_update table="sys_ux_client_script"&gt;&lt;sys_ux_client_script action="INSERT_OR_UPDATE"&gt;&lt;includes/&gt;&lt;macroponent display_value="Landing Page"&gt;d6177aeb2b132110cc0109b2ef4e3755&lt;/macroponent&gt;&lt;name&gt;data_row_3_data&lt;/name&gt;&lt;preset/&gt;&lt;required_translations&gt;[ {
  "code" : null,
  "message" : "{0} out of 5",
  "comment" : ""
} ]&lt;/required_translations&gt;&lt;script&gt;&lt;![CDATA[/**
 * @param {params} params
 * @param {api} params.api
 * @param {TransformApiHelpers} params.helpers
 */
function evaluateProperty({
    api,
    helpers
}) {
    const input = api.data.evam_popular_articles.compositeDataViews;
    for (var i = 0; i &lt; input.items.length; i++) {
        var model = input.items[i].propValues;
        if (model.model.rating != "") {
            model.detailValueTwo = helpers.translateSync("{0} out of 5", model.model.rating);
        }
    }
    return input;
}]]&gt;&lt;/script&gt;&lt;script_api_version&gt;2.0.0&lt;/script_api_version&gt;&lt;sys_class_name&gt;sys_ux_client_script&lt;/sys_class_name&gt;&lt;sys_created_by&gt;system&lt;/sys_created_by&gt;&lt;sys_created_on&gt;2023-06-14 11:48:11&lt;/sys_created_on&gt;&lt;sys_id&gt;16177aebe5132110e72aa2e74adf8449&lt;/sys_id&gt;&lt;sys_mod_count&gt;0&lt;/sys_mod_count&gt;&lt;sys_name&gt;data_row_3_data&lt;/sys_name&gt;&lt;sys_package display_value="Flow Finder" source="x_350851_flow_fi_0"&gt;18d672eb97132110974bbf1e6253afc8&lt;/sys_package&gt;&lt;sys_policy/&gt;&lt;sys_scope display_value="Flow Finder"&gt;18d672eb97132110974bbf1e6253afc8&lt;/sys_scope&gt;&lt;sys_update_name&gt;sys_ux_client_script_16177aebe5132110e72aa2e74adf8449&lt;/sys_update_name&gt;&lt;sys_updated_by&gt;system&lt;/sys_updated_by&gt;&lt;sys_updated_on&gt;2023-06-14 11:48:11&lt;/sys_updated_on&gt;&lt;target/&gt;&lt;type&gt;transform&lt;/type&gt;&lt;/sys_ux_client_script&gt;&lt;/record_update&gt;</payload>
        <payload_hash>-139901244</payload_hash>
        <record_name>data_row_3_data</record_name>
        <reverted_from/>
        <source>d4d672eb97132110974bbf1e6253afca</source>
        <source_table>sys_update_set</source_table>
        <state>previous</state>
        <sys_created_by>system</sys_created_by>
        <sys_created_on>2023-06-14 11:48:19</sys_created_on>
        <sys_id>01273eeb97132110974bbf1e6253af73</sys_id>
        <sys_mod_count>0</sys_mod_count>
        <sys_recorded_at>188b9bc366f0000001</sys_recorded_at>
        <sys_updated_by>system</sys_updated_by>
        <sys_updated_on>2023-06-14 11:48:19</sys_updated_on>
        <type>UX Client Script</type>
        <update_guid>85273eeb95132110b8caabbb33c6c072</update_guid>
        <update_guid_history>85273eeb95132110b8caabbb33c6c072:-139901244</update_guid_history>
    </sys_update_version>
    <sys_metadata_delete action="INSERT_OR_UPDATE">
        <sys_audit_delete/>
        <sys_class_name>sys_metadata_delete</sys_class_name>
        <sys_created_by>admin</sys_created_by>
        <sys_created_on>2023-06-14 12:49:09</sys_created_on>
        <sys_db_object display_value="" name="sys_ux_client_script">sys_ux_client_script</sys_db_object>
        <sys_id>1a31994f1d7c4e048e97aa4ebfe6f159</sys_id>
        <sys_metadata>16177aebe5132110e72aa2e74adf8449</sys_metadata>
        <sys_mod_count>0</sys_mod_count>
        <sys_name>data_row_3_data</sys_name>
        <sys_package display_value="Flow Finder" source="x_350851_flow_fi_0">18d672eb97132110974bbf1e6253afc8</sys_package>
        <sys_parent/>
        <sys_policy/>
        <sys_scope display_value="Flow Finder">18d672eb97132110974bbf1e6253afc8</sys_scope>
        <sys_scope_delete display_value="">987de73dd51340699b520bfeba7fe469</sys_scope_delete>
        <sys_update_name>sys_ux_client_script_16177aebe5132110e72aa2e74adf8449</sys_update_name>
        <sys_update_version display_value="sys_ux_client_script_16177aebe5132110e72aa2e74adf8449">01273eeb97132110974bbf1e6253af73</sys_update_version>
        <sys_updated_by>admin</sys_updated_by>
        <sys_updated_on>2023-06-14 12:49:09</sys_updated_on>
    </sys_metadata_delete>
</record_update>
